trajectory_planning_helpers/__init__.py
trajectory_planning_helpers/angle3pt.py
trajectory_planning_helpers/calc_ax_profile.py
trajectory_planning_helpers/calc_head_curv_an.py
trajectory_planning_helpers/calc_head_curv_num.py
trajectory_planning_helpers/calc_normal_vectors.py
trajectory_planning_helpers/calc_normal_vectors_ahead.py
trajectory_planning_helpers/calc_spline_lengths.py
trajectory_planning_helpers/calc_splines.py
trajectory_planning_helpers/calc_t_profile.py
trajectory_planning_helpers/calc_tangent_vectors.py
trajectory_planning_helpers/calc_vel_profile.py
trajectory_planning_helpers/calc_vel_profile_brake.py
trajectory_planning_helpers/check_normals_crossing.py
trajectory_planning_helpers/conv_filt.py
trajectory_planning_helpers/create_raceline.py
trajectory_planning_helpers/get_rel_path_part.py
trajectory_planning_helpers/import_veh_dyn_info.py
trajectory_planning_helpers/import_veh_dyn_info_2.py
trajectory_planning_helpers/interp_splines.py
trajectory_planning_helpers/interp_track.py
trajectory_planning_helpers/interp_track_widths.py
trajectory_planning_helpers/iqp_handler.py
trajectory_planning_helpers/nonreg_sampling.py
trajectory_planning_helpers/normalize_psi.py
trajectory_planning_helpers/opt_min_curv.py
trajectory_planning_helpers/opt_shortest_path.py
trajectory_planning_helpers/path_matching_global.py
trajectory_planning_helpers/path_matching_local.py
trajectory_planning_helpers/progressbar.py
trajectory_planning_helpers/side_of_line.py
trajectory_planning_helpers/spline_approximation.py
trajectory_planning_helpers-0.79.dist-info/LICENSE
trajectory_planning_helpers-0.79.dist-info/METADATA
trajectory_planning_helpers-0.79.dist-info/WHEEL
trajectory_planning_helpers-0.79.dist-info/top_level.txt
trajectory_planning_helpers-0.79.dist-info/RECORD
