Metadata-Version: 2.1
Name: trajectory-planning-helpers
Version: 0.79
Summary: Useful functions used for path and trajectory planning at TUM/FTM
Home-page: https://github.com/TUMFTM/trajectory_planning_helpers
Author: Alexander Heilmeier, Tim Stahl, Fabian Christ
Author-email: alexander.heilmeier@tum.de, stahl@ftm.mw.tum.de
License: UNKNOWN
Platform: UNKNOWN
Classifier: Programming Language :: Python :: 3
Classifier: Programming Language :: Python :: 3.6
Classifier: Programming Language :: Python :: 3.7
Classifier: Programming Language :: Python :: 3.8
Classifier: License :: OSI Approved :: GNU Lesser General Public License v3 (LGPLv3)
Classifier: Operating System :: OS Independent
